{
  "parent": "block/cube_all",
  "textures": {
    "side": "interiorextensions:blocks/grasspath_slab_side_lower",
    "top": "minecraft:blocks/grass_path_top",
    "bottom": "minecraft:blocks/dirt"
  },
  "elements": [
    {
      "name": "front",
      "from": [0,0,0],
      "to": [16,7,16],
      "faces": {
        "north": { "texture":  "#side" },
        "south": { "texture":  "#side" },
        "east": { "texture":  "#side" },
        "west": { "texture":  "#side" },
        "up": { "texture":  "#top" },
        "down": { "texture":  "#bottom" }
      }
    }
  ]
}